{
	"id": "config_chunking_semantic_threshold",
	"description": "Semantic chunker with explicit topic threshold on mixed-topic text",
	"tags": ["contract", "config", "chunking"],
	"call": "extract_file_sync",
	"input": {
		"path": "semantic/mixed_topics.txt",
		"config": {
			"chunking": {
				"chunker_type": "semantic",
				"topic_threshold": 0.5
			}
		}
	},
	"assertions": [
		{
			"type": "equals",
			"field": "mime_type",
			"value": "text/plain"
		},
		{
			"type": "min_length",
			"field": "content",
			"value": 100
		}
	],
	"skip": {
		"reason": "Requires chunking feature"
	}
}
